preprocess_icm/__init__.py
preprocess_icm/preprocess_element.py
preprocess_icm/preprocess_icm.py
preprocess_icm-0.44.dist-info/METADATA
preprocess_icm-0.44.dist-info/RECORD
preprocess_icm-0.44.dist-info/WHEEL
preprocess_icm-0.44.dist-info/top_level.txt
