Metadata-Version: 2.1
Name: preprocess-icm
Version: 0.44
Summary: Preprocessing incoming messages
Home-page: UNKNOWN
Author: Servicefriend
Author-email: dev@servicefriend.com
License: MIT
Platform: UNKNOWN
Classifier: Programming Language :: Python :: 2
Classifier: License :: OSI Approved :: MIT License
Classifier: Operating System :: OS Independent
